multithread_processing/__init__.py
multithread_processing/base_job.py
multithread_processing/executors/__init__.py
multithread_processing/executors/batch_work_executor.py
multithread_processing/executors/bounded_executor.py
multithread_processing/executors/fail_safe_executor.py
multithread_processing/executors/utils/__init__.py
multithread_processing/executors/utils/atomic_counter.py
multithread_processing/executors/utils/progress_logger.py
multithread_processing/executors/utils/retriable_value_error.py
multithread_processing/utils/__init__.py
multithread_processing/utils/logging_utils.py
multithread_processing/utils/utils.py
multithread_parallel_processing-1.0.0.dist-info/LICENSE
multithread_parallel_processing-1.0.0.dist-info/METADATA
multithread_parallel_processing-1.0.0.dist-info/WHEEL
multithread_parallel_processing-1.0.0.dist-info/top_level.txt
multithread_parallel_processing-1.0.0.dist-info/RECORD
