Metadata-Version: 2.1
Name: multithread-parallel-processing
Version: 1.0.0
Summary: Library support parallel processing with multi-thread
Home-page: https://github.com/hoangthanhlamm/multithread_parallel_processing
Author: VegetaIV
Author-email: hoangthanhlamm@gmail.com
Project-URL: Bug Tracker, https://github.com/hoangthanhlamm/multithread_parallel_processing
Classifier: Programming Language :: Python :: 3
Classifier: License :: OSI Approved :: MIT License
Classifier: Operating System :: OS Independent
Requires-Python: >=3.6
License-File: LICENSE
Requires-Dist: requests
